gcea/__init__.py
gcea/main.py
gcea-1.0.5.dist-info/LICENSE
gcea-1.0.5.dist-info/METADATA
gcea-1.0.5.dist-info/WHEEL
gcea-1.0.5.dist-info/entry_points.txt
gcea-1.0.5.dist-info/top_level.txt
gcea-1.0.5.dist-info/RECORD
