Metadata-Version: 2.1
Name: gcea
Version: 1.0.5
Summary: Convert files stored on put.io to mp4
Home-page: https://github.com/daveio/gcea
Author: Dave Williams
Author-email: dave@dave.io
License: License :: OSI Approved :: MIT License
Keywords: putio,put.io,convert,video,mp4
Platform: UNKNOWN
Classifier: Operating System :: OS Independent
Classifier: License :: OSI Approved :: MIT License
Classifier: Programming Language :: Python
Classifier: Programming Language :: Python :: 3.7
Classifier: Programming Language :: Python :: 3 :: Only
Requires-Python: >=3.7
Requires-Dist: putio.py
Requires-Dist: colorama
